<?xml version="1.0" encoding="UTF-8"?>
<!DOCTYPE mapper PUBLIC "-//mybatis.org//DTD Mapper 3.0//EN" "http://mybatis.org/dtd/mybatis-3-mapper.dtd">
<mapper namespace="com.new4s.weibao.dao.mapper.YqQueryMapper">
  <resultMap id="BaseResultMap" type="com.new4s.weibao.dao.entity.YqQuery">
    <!--
      WARNING - @mbg.generated
      This element is automatically generated by MyBatis Generator, do not modify.
      This element was generated on Mon May 07 16:19:57 CST 2018.
    -->
    <id column="id" jdbcType="INTEGER" property="id" />
    <result column="brand_id" jdbcType="INTEGER" property="brandId" />
    <result column="img_url" jdbcType="VARCHAR" property="imgUrl" />
    <result column="malfunction_num" jdbcType="INTEGER" property="malfunctionNum" />
    <result column="km" jdbcType="VARCHAR" property="km" />
    <result column="complete_time" jdbcType="INTEGER" property="completeTime" />
    <result column="brand_name" jdbcType="VARCHAR" property="brandName" />
    <result column="last_info_time" jdbcType="VARCHAR" property="lastInfoTime" />
    <result column="admin_name" jdbcType="VARCHAR" property="adminName" />
    <result column="engine" jdbcType="VARCHAR" property="engine" />
    <result column="vin_code" jdbcType="VARCHAR" property="vinCode" />
    <result column="right_brand" jdbcType="VARCHAR" property="rightBrand" />
    <result column="structure_status" jdbcType="CHAR" property="structureStatus" />
    <result column="engine_status" jdbcType="CHAR" property="engineStatus" />
    <result column="kilm_status" jdbcType="CHAR" property="kilmStatus" />
    <result column="is_water_status" jdbcType="CHAR" property="isWaterStatus" />
    <result column="is_fire_status" jdbcType="CHAR" property="isFireStatus" />
    <result column="safety_bag_status" jdbcType="CHAR" property="safetyBagStatus" />
    <result column="is_new_img" jdbcType="INTEGER" property="isNewImg" />
    <result column="vin_change_admin_id" jdbcType="INTEGER" property="vinChangeAdminId" />
    <result column="vin_change_time" jdbcType="INTEGER" property="vinChangeTime" />
    <result column="is_auto" jdbcType="TINYINT" property="isAuto" />
    <result column="is_urgent" jdbcType="TINYINT" property="isUrgent" />
    <result column="robot" jdbcType="INTEGER" property="robot" />
    <result column="token" jdbcType="VARCHAR" property="token" />
    <result column="transmission_status" jdbcType="CHAR" property="transmissionStatus" />
    <result column="channel_type" jdbcType="VARCHAR" property="channelType" />
    <result column="license_plate" jdbcType="VARCHAR" property="licensePlate" />
  </resultMap>
  <resultMap extends="BaseResultMap" id="ResultMapWithBLOBs" type="com.new4s.weibao.dao.entity.YqQueryWithBLOBs">
    <!--
      WARNING - @mbg.generated
      This element is automatically generated by MyBatis Generator, do not modify.
      This element was generated on Mon May 07 16:19:57 CST 2018.
    -->
    <result column="explain" jdbcType="LONGVARCHAR" property="explain" />
    <result column="query_img" jdbcType="LONGVARCHAR" property="queryImg" />
    <result column="processed_text_contents" jdbcType="LONGVARCHAR" property="processedTextContents" />
    <result column="text_contents" jdbcType="LONGVARCHAR" property="textContents" />
    <result column="contents" jdbcType="LONGVARCHAR" property="contents" />
    <result column="explain_text" jdbcType="LONGVARCHAR" property="explainText" />
    <result column="kilm_json" jdbcType="LONGVARCHAR" property="kilmJson" />
    <result column="structure_json" jdbcType="LONGVARCHAR" property="structureJson" />
    <result column="engine_json" jdbcType="LONGVARCHAR" property="engineJson" />
    <result column="safety_bag_json" jdbcType="LONGVARCHAR" property="safetyBagJson" />
    <result column="ps_json" jdbcType="LONGVARCHAR" property="psJson" />
    <result column="hs_json" jdbcType="LONGVARCHAR" property="hsJson" />
    <result column="bsx_json" jdbcType="LONGVARCHAR" property="bsxJson" />
    <result column="callbackurl" jdbcType="LONGVARCHAR" property="callbackurl" />
  </resultMap>
  <sql id="Base_Column_List">
    <!--
      WARNING - @mbg.generated
      This element is automatically generated by MyBatis Generator, do not modify.
      This element was generated on Mon May 07 16:19:57 CST 2018.
    -->
    id, brand_id, img_url, malfunction_num, km, complete_time, brand_name, last_info_time, 
    admin_name, engine, vin_code, right_brand, structure_status, engine_status, kilm_status, 
    is_water_status, is_fire_status, safety_bag_status, is_new_img, vin_change_admin_id, 
    vin_change_time, is_auto, is_urgent, robot, token, transmission_status, channel_type, 
    license_plate
  </sql>
  <sql id="Blob_Column_List">
    <!--
      WARNING - @mbg.generated
      This element is automatically generated by MyBatis Generator, do not modify.
      This element was generated on Mon May 07 16:19:57 CST 2018.
    -->
    `explain`, query_img, processed_text_contents, text_contents, contents, explain_text, 
    kilm_json, structure_json, engine_json, safety_bag_json, ps_json, hs_json, bsx_json, 
    callbackurl
  </sql>
  <select id="selectByPrimaryKey" parameterType="java.lang.Integer" resultMap="ResultMapWithBLOBs">
    <!--
      WARNING - @mbg.generated
      This element is automatically generated by MyBatis Generator, do not modify.
      This element was generated on Mon May 07 16:19:57 CST 2018.
    -->
    select 
    <include refid="Base_Column_List" />
    ,
    <include refid="Blob_Column_List" />
    from yq_query
    where id = #{id,jdbcType=INTEGER}
  </select>
  <delete id="deleteByPrimaryKey" parameterType="java.lang.Integer">
    <!--
      WARNING - @mbg.generated
      This element is automatically generated by MyBatis Generator, do not modify.
      This element was generated on Mon May 07 16:19:57 CST 2018.
    -->
    delete from yq_query
    where id = #{id,jdbcType=INTEGER}
  </delete>
  <insert id="insert" parameterType="com.new4s.weibao.dao.entity.YqQueryWithBLOBs">
    <!--
      WARNING - @mbg.generated
      This element is automatically generated by MyBatis Generator, do not modify.
      This element was generated on Mon May 07 16:19:57 CST 2018.
    -->
    insert into yq_query (id, brand_id, img_url, 
      malfunction_num, km, complete_time, 
      brand_name, last_info_time, admin_name, 
      engine, vin_code, right_brand, 
      structure_status, engine_status, kilm_status, 
      is_water_status, is_fire_status, safety_bag_status, 
      is_new_img, vin_change_admin_id, vin_change_time, 
      is_auto, is_urgent, robot, 
      token, transmission_status, channel_type, 
      license_plate, explain, query_img, 
      processed_text_contents, text_contents, 
      contents, explain_text, kilm_json, 
      structure_json, engine_json, safety_bag_json, 
      ps_json, hs_json, bsx_json, 
      callbackurl)
    values (#{id,jdbcType=INTEGER}, #{brandId,jdbcType=INTEGER}, #{imgUrl,jdbcType=VARCHAR}, 
      #{malfunctionNum,jdbcType=INTEGER}, #{km,jdbcType=VARCHAR}, #{completeTime,jdbcType=INTEGER}, 
      #{brandName,jdbcType=VARCHAR}, #{lastInfoTime,jdbcType=VARCHAR}, #{adminName,jdbcType=VARCHAR}, 
      #{engine,jdbcType=VARCHAR}, #{vinCode,jdbcType=VARCHAR}, #{rightBrand,jdbcType=VARCHAR}, 
      #{structureStatus,jdbcType=CHAR}, #{engineStatus,jdbcType=CHAR}, #{kilmStatus,jdbcType=CHAR}, 
      #{isWaterStatus,jdbcType=CHAR}, #{isFireStatus,jdbcType=CHAR}, #{safetyBagStatus,jdbcType=CHAR}, 
      #{isNewImg,jdbcType=INTEGER}, #{vinChangeAdminId,jdbcType=INTEGER}, #{vinChangeTime,jdbcType=INTEGER}, 
      #{isAuto,jdbcType=TINYINT}, #{isUrgent,jdbcType=TINYINT}, #{robot,jdbcType=INTEGER}, 
      #{token,jdbcType=VARCHAR}, #{transmissionStatus,jdbcType=CHAR}, #{channelType,jdbcType=VARCHAR}, 
      #{licensePlate,jdbcType=VARCHAR}, #{explain,jdbcType=LONGVARCHAR}, #{queryImg,jdbcType=LONGVARCHAR}, 
      #{processedTextContents,jdbcType=LONGVARCHAR}, #{textContents,jdbcType=LONGVARCHAR}, 
      #{contents,jdbcType=LONGVARCHAR}, #{explainText,jdbcType=LONGVARCHAR}, #{kilmJson,jdbcType=LONGVARCHAR}, 
      #{structureJson,jdbcType=LONGVARCHAR}, #{engineJson,jdbcType=LONGVARCHAR}, #{safetyBagJson,jdbcType=LONGVARCHAR}, 
      #{psJson,jdbcType=LONGVARCHAR}, #{hsJson,jdbcType=LONGVARCHAR}, #{bsxJson,jdbcType=LONGVARCHAR}, 
      #{callbackurl,jdbcType=LONGVARCHAR})
  </insert>
  <insert id="insertSelective" parameterType="com.new4s.weibao.dao.entity.YqQueryWithBLOBs">
    <!--
      WARNING - @mbg.generated
      This element is automatically generated by MyBatis Generator, do not modify.
      This element was generated on Mon May 07 16:19:57 CST 2018.
    -->
    insert into yq_query
    <trim prefix="(" suffix=")" suffixOverrides=",">
      <if test="id != null">
        id,
      </if>
      <if test="brandId != null">
        brand_id,
      </if>
      <if test="imgUrl != null">
        img_url,
      </if>
      <if test="malfunctionNum != null">
        malfunction_num,
      </if>
      <if test="km != null">
        km,
      </if>
      <if test="completeTime != null">
        complete_time,
      </if>
      <if test="brandName != null">
        brand_name,
      </if>
      <if test="lastInfoTime != null">
        last_info_time,
      </if>
      <if test="adminName != null">
        admin_name,
      </if>
      <if test="engine != null">
        engine,
      </if>
      <if test="vinCode != null">
        vin_code,
      </if>
      <if test="rightBrand != null">
        right_brand,
      </if>
      <if test="structureStatus != null">
        structure_status,
      </if>
      <if test="engineStatus != null">
        engine_status,
      </if>
      <if test="kilmStatus != null">
        kilm_status,
      </if>
      <if test="isWaterStatus != null">
        is_water_status,
      </if>
      <if test="isFireStatus != null">
        is_fire_status,
      </if>
      <if test="safetyBagStatus != null">
        safety_bag_status,
      </if>
      <if test="isNewImg != null">
        is_new_img,
      </if>
      <if test="vinChangeAdminId != null">
        vin_change_admin_id,
      </if>
      <if test="vinChangeTime != null">
        vin_change_time,
      </if>
      <if test="isAuto != null">
        is_auto,
      </if>
      <if test="isUrgent != null">
        is_urgent,
      </if>
      <if test="robot != null">
        robot,
      </if>
      <if test="token != null">
        token,
      </if>
      <if test="transmissionStatus != null">
        transmission_status,
      </if>
      <if test="channelType != null">
        channel_type,
      </if>
      <if test="licensePlate != null">
        license_plate,
      </if>
      <if test="explain != null">
        explain,
      </if>
      <if test="queryImg != null">
        query_img,
      </if>
      <if test="processedTextContents != null">
        processed_text_contents,
      </if>
      <if test="textContents != null">
        text_contents,
      </if>
      <if test="contents != null">
        contents,
      </if>
      <if test="explainText != null">
        explain_text,
      </if>
      <if test="kilmJson != null">
        kilm_json,
      </if>
      <if test="structureJson != null">
        structure_json,
      </if>
      <if test="engineJson != null">
        engine_json,
      </if>
      <if test="safetyBagJson != null">
        safety_bag_json,
      </if>
      <if test="psJson != null">
        ps_json,
      </if>
      <if test="hsJson != null">
        hs_json,
      </if>
      <if test="bsxJson != null">
        bsx_json,
      </if>
      <if test="callbackurl != null">
        callbackurl,
      </if>
    </trim>
    <trim prefix="values (" suffix=")" suffixOverrides=",">
      <if test="id != null">
        #{id,jdbcType=INTEGER},
      </if>
      <if test="brandId != null">
        #{brandId,jdbcType=INTEGER},
      </if>
      <if test="imgUrl != null">
        #{imgUrl,jdbcType=VARCHAR},
      </if>
      <if test="malfunctionNum != null">
        #{malfunctionNum,jdbcType=INTEGER},
      </if>
      <if test="km != null">
        #{km,jdbcType=VARCHAR},
      </if>
      <if test="completeTime != null">
        #{completeTime,jdbcType=INTEGER},
      </if>
      <if test="brandName != null">
        #{brandName,jdbcType=VARCHAR},
      </if>
      <if test="lastInfoTime != null">
        #{lastInfoTime,jdbcType=VARCHAR},
      </if>
      <if test="adminName != null">
        #{adminName,jdbcType=VARCHAR},
      </if>
      <if test="engine != null">
        #{engine,jdbcType=VARCHAR},
      </if>
      <if test="vinCode != null">
        #{vinCode,jdbcType=VARCHAR},
      </if>
      <if test="rightBrand != null">
        #{rightBrand,jdbcType=VARCHAR},
      </if>
      <if test="structureStatus != null">
        #{structureStatus,jdbcType=CHAR},
      </if>
      <if test="engineStatus != null">
        #{engineStatus,jdbcType=CHAR},
      </if>
      <if test="kilmStatus != null">
        #{kilmStatus,jdbcType=CHAR},
      </if>
      <if test="isWaterStatus != null">
        #{isWaterStatus,jdbcType=CHAR},
      </if>
      <if test="isFireStatus != null">
        #{isFireStatus,jdbcType=CHAR},
      </if>
      <if test="safetyBagStatus != null">
        #{safetyBagStatus,jdbcType=CHAR},
      </if>
      <if test="isNewImg != null">
        #{isNewImg,jdbcType=INTEGER},
      </if>
      <if test="vinChangeAdminId != null">
        #{vinChangeAdminId,jdbcType=INTEGER},
      </if>
      <if test="vinChangeTime != null">
        #{vinChangeTime,jdbcType=INTEGER},
      </if>
      <if test="isAuto != null">
        #{isAuto,jdbcType=TINYINT},
      </if>
      <if test="isUrgent != null">
        #{isUrgent,jdbcType=TINYINT},
      </if>
      <if test="robot != null">
        #{robot,jdbcType=INTEGER},
      </if>
      <if test="token != null">
        #{token,jdbcType=VARCHAR},
      </if>
      <if test="transmissionStatus != null">
        #{transmissionStatus,jdbcType=CHAR},
      </if>
      <if test="channelType != null">
        #{channelType,jdbcType=VARCHAR},
      </if>
      <if test="licensePlate != null">
        #{licensePlate,jdbcType=VARCHAR},
      </if>
      <if test="explain != null">
        #{explain,jdbcType=LONGVARCHAR},
      </if>
      <if test="queryImg != null">
        #{queryImg,jdbcType=LONGVARCHAR},
      </if>
      <if test="processedTextContents != null">
        #{processedTextContents,jdbcType=LONGVARCHAR},
      </if>
      <if test="textContents != null">
        #{textContents,jdbcType=LONGVARCHAR},
      </if>
      <if test="contents != null">
        #{contents,jdbcType=LONGVARCHAR},
      </if>
      <if test="explainText != null">
        #{explainText,jdbcType=LONGVARCHAR},
      </if>
      <if test="kilmJson != null">
        #{kilmJson,jdbcType=LONGVARCHAR},
      </if>
      <if test="structureJson != null">
        #{structureJson,jdbcType=LONGVARCHAR},
      </if>
      <if test="engineJson != null">
        #{engineJson,jdbcType=LONGVARCHAR},
      </if>
      <if test="safetyBagJson != null">
        #{safetyBagJson,jdbcType=LONGVARCHAR},
      </if>
      <if test="psJson != null">
        #{psJson,jdbcType=LONGVARCHAR},
      </if>
      <if test="hsJson != null">
        #{hsJson,jdbcType=LONGVARCHAR},
      </if>
      <if test="bsxJson != null">
        #{bsxJson,jdbcType=LONGVARCHAR},
      </if>
      <if test="callbackurl != null">
        #{callbackurl,jdbcType=LONGVARCHAR},
      </if>
    </trim>
  </insert>
  <update id="updateByPrimaryKeySelective" parameterType="com.new4s.weibao.dao.entity.YqQueryWithBLOBs">
    <!--
      WARNING - @mbg.generated
      This element is automatically generated by MyBatis Generator, do not modify.
      This element was generated on Mon May 07 16:19:57 CST 2018.
    -->
    update yq_query
    <set>
      <if test="brandId != null">
        brand_id = #{brandId,jdbcType=INTEGER},
      </if>
      <if test="imgUrl != null">
        img_url = #{imgUrl,jdbcType=VARCHAR},
      </if>
      <if test="malfunctionNum != null">
        malfunction_num = #{malfunctionNum,jdbcType=INTEGER},
      </if>
      <if test="km != null">
        km = #{km,jdbcType=VARCHAR},
      </if>
      <if test="completeTime != null">
        complete_time = #{completeTime,jdbcType=INTEGER},
      </if>
      <if test="brandName != null">
        brand_name = #{brandName,jdbcType=VARCHAR},
      </if>
      <if test="lastInfoTime != null">
        last_info_time = #{lastInfoTime,jdbcType=VARCHAR},
      </if>
      <if test="adminName != null">
        admin_name = #{adminName,jdbcType=VARCHAR},
      </if>
      <if test="engine != null">
        engine = #{engine,jdbcType=VARCHAR},
      </if>
      <if test="vinCode != null">
        vin_code = #{vinCode,jdbcType=VARCHAR},
      </if>
      <if test="rightBrand != null">
        right_brand = #{rightBrand,jdbcType=VARCHAR},
      </if>
      <if test="structureStatus != null">
        structure_status = #{structureStatus,jdbcType=CHAR},
      </if>
      <if test="engineStatus != null">
        engine_status = #{engineStatus,jdbcType=CHAR},
      </if>
      <if test="kilmStatus != null">
        kilm_status = #{kilmStatus,jdbcType=CHAR},
      </if>
      <if test="isWaterStatus != null">
        is_water_status = #{isWaterStatus,jdbcType=CHAR},
      </if>
      <if test="isFireStatus != null">
        is_fire_status = #{isFireStatus,jdbcType=CHAR},
      </if>
      <if test="safetyBagStatus != null">
        safety_bag_status = #{safetyBagStatus,jdbcType=CHAR},
      </if>
      <if test="isNewImg != null">
        is_new_img = #{isNewImg,jdbcType=INTEGER},
      </if>
      <if test="vinChangeAdminId != null">
        vin_change_admin_id = #{vinChangeAdminId,jdbcType=INTEGER},
      </if>
      <if test="vinChangeTime != null">
        vin_change_time = #{vinChangeTime,jdbcType=INTEGER},
      </if>
      <if test="isAuto != null">
        is_auto = #{isAuto,jdbcType=TINYINT},
      </if>
      <if test="isUrgent != null">
        is_urgent = #{isUrgent,jdbcType=TINYINT},
      </if>
      <if test="robot != null">
        robot = #{robot,jdbcType=INTEGER},
      </if>
      <if test="token != null">
        token = #{token,jdbcType=VARCHAR},
      </if>
      <if test="transmissionStatus != null">
        transmission_status = #{transmissionStatus,jdbcType=CHAR},
      </if>
      <if test="channelType != null">
        channel_type = #{channelType,jdbcType=VARCHAR},
      </if>
      <if test="licensePlate != null">
        license_plate = #{licensePlate,jdbcType=VARCHAR},
      </if>
      <if test="explain != null">
        explain = #{explain,jdbcType=LONGVARCHAR},
      </if>
      <if test="queryImg != null">
        query_img = #{queryImg,jdbcType=LONGVARCHAR},
      </if>
      <if test="processedTextContents != null">
        processed_text_contents = #{processedTextContents,jdbcType=LONGVARCHAR},
      </if>
      <if test="textContents != null">
        text_contents = #{textContents,jdbcType=LONGVARCHAR},
      </if>
      <if test="contents != null">
        contents = #{contents,jdbcType=LONGVARCHAR},
      </if>
      <if test="explainText != null">
        explain_text = #{explainText,jdbcType=LONGVARCHAR},
      </if>
      <if test="kilmJson != null">
        kilm_json = #{kilmJson,jdbcType=LONGVARCHAR},
      </if>
      <if test="structureJson != null">
        structure_json = #{structureJson,jdbcType=LONGVARCHAR},
      </if>
      <if test="engineJson != null">
        engine_json = #{engineJson,jdbcType=LONGVARCHAR},
      </if>
      <if test="safetyBagJson != null">
        safety_bag_json = #{safetyBagJson,jdbcType=LONGVARCHAR},
      </if>
      <if test="psJson != null">
        ps_json = #{psJson,jdbcType=LONGVARCHAR},
      </if>
      <if test="hsJson != null">
        hs_json = #{hsJson,jdbcType=LONGVARCHAR},
      </if>
      <if test="bsxJson != null">
        bsx_json = #{bsxJson,jdbcType=LONGVARCHAR},
      </if>
      <if test="callbackurl != null">
        callbackurl = #{callbackurl,jdbcType=LONGVARCHAR},
      </if>
    </set>
    where id = #{id,jdbcType=INTEGER}
  </update>
  <update id="updateByPrimaryKeyWithBLOBs" parameterType="com.new4s.weibao.dao.entity.YqQueryWithBLOBs">
    <!--
      WARNING - @mbg.generated
      This element is automatically generated by MyBatis Generator, do not modify.
      This element was generated on Mon May 07 16:19:57 CST 2018.
    -->
    update yq_query
    set brand_id = #{brandId,jdbcType=INTEGER},
      img_url = #{imgUrl,jdbcType=VARCHAR},
      malfunction_num = #{malfunctionNum,jdbcType=INTEGER},
      km = #{km,jdbcType=VARCHAR},
      complete_time = #{completeTime,jdbcType=INTEGER},
      brand_name = #{brandName,jdbcType=VARCHAR},
      last_info_time = #{lastInfoTime,jdbcType=VARCHAR},
      admin_name = #{adminName,jdbcType=VARCHAR},
      engine = #{engine,jdbcType=VARCHAR},
      vin_code = #{vinCode,jdbcType=VARCHAR},
      right_brand = #{rightBrand,jdbcType=VARCHAR},
      structure_status = #{structureStatus,jdbcType=CHAR},
      engine_status = #{engineStatus,jdbcType=CHAR},
      kilm_status = #{kilmStatus,jdbcType=CHAR},
      is_water_status = #{isWaterStatus,jdbcType=CHAR},
      is_fire_status = #{isFireStatus,jdbcType=CHAR},
      safety_bag_status = #{safetyBagStatus,jdbcType=CHAR},
      is_new_img = #{isNewImg,jdbcType=INTEGER},
      vin_change_admin_id = #{vinChangeAdminId,jdbcType=INTEGER},
      vin_change_time = #{vinChangeTime,jdbcType=INTEGER},
      is_auto = #{isAuto,jdbcType=TINYINT},
      is_urgent = #{isUrgent,jdbcType=TINYINT},
      robot = #{robot,jdbcType=INTEGER},
      token = #{token,jdbcType=VARCHAR},
      transmission_status = #{transmissionStatus,jdbcType=CHAR},
      channel_type = #{channelType,jdbcType=VARCHAR},
      license_plate = #{licensePlate,jdbcType=VARCHAR},
      explain = #{explain,jdbcType=LONGVARCHAR},
      query_img = #{queryImg,jdbcType=LONGVARCHAR},
      processed_text_contents = #{processedTextContents,jdbcType=LONGVARCHAR},
      text_contents = #{textContents,jdbcType=LONGVARCHAR},
      contents = #{contents,jdbcType=LONGVARCHAR},
      explain_text = #{explainText,jdbcType=LONGVARCHAR},
      kilm_json = #{kilmJson,jdbcType=LONGVARCHAR},
      structure_json = #{structureJson,jdbcType=LONGVARCHAR},
      engine_json = #{engineJson,jdbcType=LONGVARCHAR},
      safety_bag_json = #{safetyBagJson,jdbcType=LONGVARCHAR},
      ps_json = #{psJson,jdbcType=LONGVARCHAR},
      hs_json = #{hsJson,jdbcType=LONGVARCHAR},
      bsx_json = #{bsxJson,jdbcType=LONGVARCHAR},
      callbackurl = #{callbackurl,jdbcType=LONGVARCHAR}
    where id = #{id,jdbcType=INTEGER}
  </update>
  <update id="updateByPrimaryKey" parameterType="com.new4s.weibao.dao.entity.YqQuery">
    <!--
      WARNING - @mbg.generated
      This element is automatically generated by MyBatis Generator, do not modify.
      This element was generated on Mon May 07 16:19:57 CST 2018.
    -->
    update yq_query
    set brand_id = #{brandId,jdbcType=INTEGER},
      img_url = #{imgUrl,jdbcType=VARCHAR},
      malfunction_num = #{malfunctionNum,jdbcType=INTEGER},
      km = #{km,jdbcType=VARCHAR},
      complete_time = #{completeTime,jdbcType=INTEGER},
      brand_name = #{brandName,jdbcType=VARCHAR},
      last_info_time = #{lastInfoTime,jdbcType=VARCHAR},
      admin_name = #{adminName,jdbcType=VARCHAR},
      engine = #{engine,jdbcType=VARCHAR},
      vin_code = #{vinCode,jdbcType=VARCHAR},
      right_brand = #{rightBrand,jdbcType=VARCHAR},
      structure_status = #{structureStatus,jdbcType=CHAR},
      engine_status = #{engineStatus,jdbcType=CHAR},
      kilm_status = #{kilmStatus,jdbcType=CHAR},
      is_water_status = #{isWaterStatus,jdbcType=CHAR},
      is_fire_status = #{isFireStatus,jdbcType=CHAR},
      safety_bag_status = #{safetyBagStatus,jdbcType=CHAR},
      is_new_img = #{isNewImg,jdbcType=INTEGER},
      vin_change_admin_id = #{vinChangeAdminId,jdbcType=INTEGER},
      vin_change_time = #{vinChangeTime,jdbcType=INTEGER},
      is_auto = #{isAuto,jdbcType=TINYINT},
      is_urgent = #{isUrgent,jdbcType=TINYINT},
      robot = #{robot,jdbcType=INTEGER},
      token = #{token,jdbcType=VARCHAR},
      transmission_status = #{transmissionStatus,jdbcType=CHAR},
      channel_type = #{channelType,jdbcType=VARCHAR},
      license_plate = #{licensePlate,jdbcType=VARCHAR}
    where id = #{id,jdbcType=INTEGER}
  </update>
  
  <select id="selectByVin" parameterType="java.lang.String" resultMap="ResultMapWithBLOBs">
    <!--
      WARNING - @mbg.generated
      This element is automatically generated by MyBatis Generator, do not modify.
      This element was generated on Mon May 07 16:19:57 CST 2018.
    -->
    select 
    <include refid="Base_Column_List" />
    ,
    <include refid="Blob_Column_List" />
    from yq_query
    where vin_code = #{vinCode,jdbcType=VARCHAR} order by id limit 1
  </select>
</mapper>